.gitignore
CHANGES.rst
MANIFEST.in
README.rst
bootstrap.py
buildout.cfg
setup.py
collective/__init__.py
collective.realestatebroker.egg-info/PKG-INFO
collective.realestatebroker.egg-info/SOURCES.txt
collective.realestatebroker.egg-info/dependency_links.txt
collective.realestatebroker.egg-info/entry_points.txt
collective.realestatebroker.egg-info/namespace_packages.txt
collective.realestatebroker.egg-info/not-zip-safe
collective.realestatebroker.egg-info/requires.txt
collective.realestatebroker.egg-info/top_level.txt
collective/realestatebroker/README.txt
collective/realestatebroker/TODO.txt
collective/realestatebroker/__init__.py
collective/realestatebroker/config.py
collective/realestatebroker/configure.zcml
collective/realestatebroker/interfaces.py
collective/realestatebroker/migration.py
collective/realestatebroker/rebuild_i18n.sh
collective/realestatebroker/setuphandlers.py
collective/realestatebroker/utils.py
collective/realestatebroker/version.txt
collective/realestatebroker/Extensions/Install.py
collective/realestatebroker/adapters/__init__.py
collective/realestatebroker/adapters/configure.zcml
collective/realestatebroker/adapters/floor.py
collective/realestatebroker/adapters/interfaces.py
collective/realestatebroker/adapters/map.py
collective/realestatebroker/browser/README.txt
collective/realestatebroker/browser/__init__.py
collective/realestatebroker/browser/album.py
collective/realestatebroker/browser/base.py
collective/realestatebroker/browser/commercial.py
collective/realestatebroker/browser/configure.zcml
collective/realestatebroker/browser/controlpanel.py
collective/realestatebroker/browser/floor.py
collective/realestatebroker/browser/interfaces.py
collective/realestatebroker/browser/map.py
collective/realestatebroker/browser/pdf.txt
collective/realestatebroker/browser/residential.py
collective/realestatebroker/browser/viewlets.py
collective/realestatebroker/browser/images/README.txt
collective/realestatebroker/browser/images/commercial_icon.gif
collective/realestatebroker/browser/images/commercial_icon.gif.metadata
collective/realestatebroker/browser/images/marker-commercial.png
collective/realestatebroker/browser/images/marker-commercial.png.metadata
collective/realestatebroker/browser/images/marker-residential.png
collective/realestatebroker/browser/images/marker-residential.png.metadata
collective/realestatebroker/browser/images/media-seek-backward.png
