Metadata-Version: 1.0
Name: collective.realestatebroker
Version: 2.3
Summary: An easy and professional way to publish real estate objects on your Plone website
Home-page: http://plone.org/products/realestatebroker
Author: Zest software
Author-email: info@zestsoftware.nl
License: GPL
Keywords: realestate makelaar plone
Platform: UNKNOWN
Classifier: Framework :: Plone
Classifier: Framework :: Plone :: 3.2
Classifier: Framework :: Plone :: 3.3
Classifier: Framework :: Zope2
Classifier: Framework :: Zope3
Classifier: Programming Language :: Python
Classifier: Topic :: Software Development :: Libraries :: Python Modules
